README.md
setup.py
epitopepredict/__init__.py
epitopepredict/analysis.py
epitopepredict/app.py
epitopepredict/base.py
epitopepredict/cluster.py
epitopepredict/config.py
epitopepredict/dashboard.py
epitopepredict/description.txt
epitopepredict/flask_serve.py
epitopepredict/mhclearn.py
epitopepredict/neo.py
epitopepredict/neo_tests.py
epitopepredict/peptutils.py
epitopepredict/plotting.py
epitopepredict/pymolutils.py
epitopepredict/seqdepot.py
epitopepredict/seqdepot_py3.py
epitopepredict/sequtils.py
epitopepredict/tepitope.py
epitopepredict/tests.py
epitopepredict/tornado_serve.py
epitopepredict/utilities.py
epitopepredict/web.py
epitopepredict.egg-info/PKG-INFO
epitopepredict.egg-info/SOURCES.txt
epitopepredict.egg-info/dependency_links.txt
epitopepredict.egg-info/entry_points.txt
epitopepredict.egg-info/requires.txt
epitopepredict.egg-info/top_level.txt
epitopepredict/mhcdata/NLF.csv
epitopepredict/mhcdata/OETMAP.csv
epitopepredict/mhcdata/binding_data_2013.zip
epitopepredict/mhcdata/blosum50.csv
epitopepredict/mhcdata/blosum62.csv
epitopepredict/mhcdata/curated_training_data.no_mass_spec.zip
epitopepredict/mhcdata/iedb_mhc1_alleles.csv
epitopepredict/mhcdata/iedb_mhc2_alleles.csv
epitopepredict/mhcdata/pmbec.csv
epitopepredict/mhcdata/quantiles_basicmhc1.csv
epitopepredict/mhcdata/quantiles_iedbmhc1.csv
epitopepredict/mhcdata/quantiles_iedbmhc2.csv
epitopepredict/mhcdata/quantiles_mhcflurry.csv
epitopepredict/mhcdata/quantiles_mhcnuggets.csv
epitopepredict/mhcdata/quantiles_netmhciipan.csv
epitopepredict/mhcdata/quantiles_netmhcpan.csv
epitopepredict/mhcdata/quantiles_tepitope.csv
epitopepredict/mhcnuggets/mhcnuggets_lstm/H-2-DB.h5
epitopepredict/mhcnuggets/mhcnuggets_lstm/H-2-KB.h5
epitopepredict/mhcnuggets/mhcnuggets_lstm/H-2-KD.h5
epitopepredict/mhcnuggets/mhcnuggets_lstm/HLA-A0101.h5
epitopepredict/mhcnuggets/mhcnuggets_lstm/HLA-A0201.h5
epitopepredict/mhcnuggets/mhcnuggets_lstm/HLA-A0202.h5
epitopepredict/mhcnuggets/mhcnuggets_lstm/HLA-A0203.h5
epitopepredict/mhcnuggets/mhcnuggets_lstm/HLA-A0206.h5
epitopepredict/mhcnuggets/mhcnuggets_lstm/HLA-A0301.h5
epitopepredict/mhcnuggets/mhcnuggets_lstm/HLA-A1101.h5
epitopepredict/mhcnuggets/mhcnuggets_lstm/HLA-A2301.h5
