Metadata-Version: 1.1
Name: epitopepredict
Version: 0.5.0
Summary: Python package for epitope prediction
Home-page: https://github.com/dmnfarrell/epitopepredict
Author: Damien Farrell
Author-email: farrell.damien@gmail.com
License: GPL v3
Keywords: epitope,mhc,immunology,biology
Platform: UNKNOWN
Classifier: Operating System :: OS Independent
Classifier: Programming Language :: Python :: 2.7
Classifier: Programming Language :: Python :: 3.6
Classifier: Operating System :: MacOS :: MacOS X
Classifier: Operating System :: Microsoft :: Windows
Classifier: Operating System :: POSIX
Classifier: License :: OSI Approved :: GNU General Public License v3 (GPLv3)
Classifier: Development Status :: 4 - Beta
Classifier: Intended Audience :: Science/Research
Classifier: Topic :: Scientific/Engineering :: Bio-Informatics
